pdfplumber_i/__init__.py
pdfplumber_i/_version.py
pdfplumber_i/cli.py
pdfplumber_i/container.py
pdfplumber_i/display.py
pdfplumber_i/page.py
pdfplumber_i/pdf.py
pdfplumber_i/table.py
pdfplumber_i/utils.py
pdfplumber_i-0.6.6.dist-info/METADATA
pdfplumber_i-0.6.6.dist-info/WHEEL
pdfplumber_i-0.6.6.dist-info/entry_points.txt
pdfplumber_i-0.6.6.dist-info/top_level.txt
pdfplumber_i-0.6.6.dist-info/RECORD
