Metadata-Version: 2.1
Name: pdfplumber-i
Version: 0.6.6
Summary: Plumb a PDF for detailed information about each char, rectangle, and line.
Home-page: UNKNOWN
Author: UNKNOWN
Author-email: UNKNOWN
License: UNKNOWN
Platform: UNKNOWN
Requires-Dist: chardet
Requires-Dist: pycryptodome
Requires-Dist: unicodecsv (>=0.14.1)
Requires-Dist: pdfminer.six-i (==20190823)
Requires-Dist: pillow (>=3.0.0)
Requires-Dist: wand
Requires-Dist: networkx
